Workbook

Sheet Read Me
A1: ATM Recycling — Benefit Quantification Model
A3: Purpose | B3: Quantifies the annual $ benefit of converting cash-dispense-only ATMs to cash-recycling ATMs, based on two avoidance mechanisms: (1) avoided out-of-cash (OOC) events, and (2) avoided deposit-full events.
A5: How the logic works | B5: Recycling ATMs reuse customer cash deposits to fund withdrawals from the same cassette set. This lowers net cash-out burn (fewer/later OOC events) and lowers deposit-module fill rate (fewer/later deposit-full events), because deposited notes are continuously recirculated instead of sitting in a separate module until a CIT pickup.
A7: Sheets in this workbook
A8: Assumptions | B8: All editable inputs — fleet size, baseline vs. recycling event rates, and cost components per event. Yellow cells = your inputs.
A9: OOC_Benefit | B9: Quantifies annual $ benefit from avoided out-of-cash events.
A10: DepositFull_Benefit | B10: Quantifies annual $ benefit from avoided deposit-full events.
A11: Summary | B11: Combines both benefit streams, nets against conversion cost, and computes payback / 3-yr ROI.
A13: Color legend
A14: Yellow fill, blue text | B14: Input — edit these. Every other cell is a live formula; do not overwrite.
A15: Black text | B15: Formula, calculated within the same sheet.
A16: Green text | B16: Formula linking to another sheet.
A18: Example values | B18: Illustrative starting values are pre-filled in the Assumptions sheet (typical ranges seen in fleet cash-management studies). Replace them with your own fleet's observed OOC/deposit-full rates and cost figures before relying on the output.
A20: Note on cost figures | B20: All per-event cost figures (fee income lost, emergency CIT trip cost, dissatisfaction/reputational cost) are placeholders you supply — no external benchmark is cited. Replace with your organization's actual finance/ops figures where available.

Sheet Assumptions
A1: Key Assumptions & Inputs
A2: Edit only the yellow cells. All figures are per-ATM-per-month unless stated otherwise.
A4: A. Fleet Parameters
B5: Value | C5: Unit
A6: Number of ATMs converted to recycling | B6: 100 | C6: ATMs
A7: Analysis period | B7: 12 | C7: months
A8: Conversion cost per ATM (capex/opex, one-time) | B8: 350000 | C8: $ per ATM
A10: B. Out-of-Cash (OOC) Event Parameters
B11: Baseline (Non-Recycling) | C11: Recycling | D11: Unit
A12: OOC events per ATM per month | B12: 1.2 | C12: 0.3 | D12: events/ATM/month
A13: Avg. transactions lost per OOC event (until replenished) | B13: 45 | D13: txns/event (same for both — applied to reduced event count)
A14: Avg. fee / interchange income per withdrawal txn | B14: 18 | D14: $/txn
A15: Emergency CIT replenishment cost per OOC event | B15: 2500 | D15: $/event
A16: Customer dissatisfaction / reputational cost per OOC event | B16: 150 | D16: $/event (proxy — churn risk, complaint handling, brand cost)
A18: C. Deposit-Full Event Parameters
B19: Baseline (Non-Recycling) | C19: Recycling | D19: Unit
A20: Deposit-full events per ATM per month | B20: 0.8 | C20: 0.15 | D20: events/ATM/month
A21: Avg. deposit transactions rejected/redirected per event | B21: 20 | D21: txns/event
A22: Avg. fee income per deposit txn (lost when redirected) | B22: 5 | D22: $/txn (set to 0 if deposits are fee-free)
A23: Emergency CIT pickup cost per deposit-full event | B23: 2500 | D23: $/event
A24: Customer dissatisfaction / reputational cost per deposit-full event | B24: 150 | D24: $/event (proxy)

Sheet OOC_Benefit
A1: Benefit from Avoided Out-of-Cash (OOC) Events
A2: All inputs are linked (green) from the Assumptions sheet. Nothing here needs editing.
A4: 1. Cost per OOC Event (cost structure — same whether baseline or recycling)
A5: Fee/interchange income lost (txns lost x fee per txn) | B5: =Assumptions!$B$13*Assumptions!$B$14 -> 810
A6: Emergency CIT replenishment cost | B6: =Assumptions!$B$15 -> 2500
A7: Customer dissatisfaction / reputational cost | B7: =Assumptions!$B$16 -> 150
A8: Total cost per OOC event | B8: =B5+B6+B7 -> 3460
A10: 2. Monthly & Annual Benefit (per ATM, then fleet-wide)
B11: Baseline (Non-Recycling) | C11: Recycling | D11: Reduction / Benefit
A12: OOC events per ATM per month | B12: =Assumptions!$B$12 -> 1.2 | C12: =Assumptions!$C$12 -> 0.3 | D12: =B12-C12 -> 0.9
A13: Cost per event ($) | B13: =$B$8 -> 3460 | C13: =$B$8 -> 3460
A14: Monthly cost per ATM | B14: =B12*B13 -> 4152 | C14: =C12*C13 -> 1038 | D14: =B14-C14 -> 3114
A15: Annual cost per ATM (x analysis period) | B15: =B14*Assumptions!$B$7 -> 49824 | C15: =C14*Assumptions!$B$7 -> 12456 | D15: =B15-C15 -> 37368
A16: Fleet-wide annual cost (x number of ATMs) | B16: =B15*Assumptions!$B$6 -> 4982400 | C16: =C15*Assumptions!$B$6 -> 1245600 | D16: =B16-C16 -> 3736800
A18: 3. Result
A19: Annual $ Benefit — Avoided OOC Events (fleet-wide) | B19: =D16 -> 3736800

Sheet DepositFull_Benefit
A1: Benefit from Avoided Deposit-Full Events
A2: All inputs are linked (green) from the Assumptions sheet. Nothing here needs editing.
A4: 1. Cost per Deposit-Full Event
A5: Fee income lost (deposit txns redirected x fee per txn) | B5: =Assumptions!$B$21*Assumptions!$B$22 -> 100
A6: Emergency CIT pickup cost | B6: =Assumptions!$B$23 -> 2500
A7: Customer dissatisfaction / reputational cost | B7: =Assumptions!$B$24 -> 150
A8: Total cost per deposit-full event | B8: =B5+B6+B7 -> 2750
A10: 2. Monthly & Annual Benefit (per ATM, then fleet-wide)
B11: Baseline (Non-Recycling) | C11: Recycling | D11: Reduction / Benefit
A12: Deposit-full events per ATM per month | B12: =Assumptions!$B$20 -> 0.8 | C12: =Assumptions!$C$20 -> 0.15 | D12: =B12-C12 -> 0.65
A13: Cost per event ($) | B13: =$B$8 -> 2750 | C13: =$B$8 -> 2750
A14: Monthly cost per ATM | B14: =B12*B13 -> 2200 | C14: =C12*C13 -> 412.5 | D14: =B14-C14 -> 1787.5
A15: Annual cost per ATM (x analysis period) | B15: =B14*Assumptions!$B$7 -> 26400 | C15: =C14*Assumptions!$B$7 -> 4950 | D15: =B15-C15 -> 21450
A16: Fleet-wide annual cost (x number of ATMs) | B16: =B15*Assumptions!$B$6 -> 2640000 | C16: =C15*Assumptions!$B$6 -> 495000 | D16: =B16-C16 -> 2145000
A18: 3. Result
A19: Annual $ Benefit — Avoided Deposit-Full Events (fleet-wide) | B19: =D16 -> 2145000

Sheet Summary
A1: ATM Recycling — Combined Benefit Summary
A2: Pulls results from OOC_Benefit and DepositFull_Benefit sheets. Edit Assumptions sheet only.
A4: 1. Annual Benefit by Avoidance Category (fleet-wide)
B5: Annual $ Benefit
A6: Avoided out-of-cash (OOC) events | B6: =OOC_Benefit!$B$19 -> 3736800
A7: Avoided deposit-full events | B7: =DepositFull_Benefit!$B$19 -> 2145000
A8: Total annual benefit | B8: =B6+B7 -> 5881800
A10: 2. Investment Case
A11: Number of ATMs converted | B11: =Assumptions!$B$6 -> 100
A12: Conversion cost per ATM | B12: =Assumptions!$B$8 -> 350000
A13: Total fleet conversion cost | B13: =Assumptions!$B$6*Assumptions!$B$8 -> 35000000
A14: Simple payback period | B14: =B13/(B8/12) -> 71.406712 | C14: months
A15: Year 1 net benefit (benefit less conversion cost) | B15: =B8-B13 -> -29118200
A16: 3-year net benefit (recurring benefit x3, less one-time conversion cost) | B16: =(B8*3)-B13 -> -17354600
A17: 3-year ROI (%) | B17: =B16/B13 -> -0.49584571
A19: 3. Headline Result
A20: Total Annual $ Benefit of Recycling Conversion | B20: =B8 -> 5881800
A22: Benefit is a modeled avoidance value: (baseline event rate − recycling event rate) x cost per event x fleet size x period, summed across the OOC and deposit-full streams. It assumes the recycling event rates on the Assumptions sheet are achieved in practice — validate against pilot-fleet data once available.
