Workbook

Sheet Assumptions
A1: 3-Year Benefit Calculation Model — Assumptions
A3: Financial Assumptions
A4: Annual discount rate (cost of capital) | B4: 0.1 | C4: Used to compute NPV of net benefits
A5: Annual cost escalation rate | B5: 0.03 | C5: Applied to recurring/operating costs each year
A7: Benefit Realization Ramp-Up (% of full run-rate benefit achieved)
A8: Year 1 realization % | B8: 0.4
A9: Year 2 realization % | B9: 0.75
A10: Year 3 realization % | B10: 1
A11: → Adjust these if benefit adoption ramps up over time (typical for process/tech rollouts)
A13: Cost Inputs (Year 1 base; escalates in later years)
A14: One-time implementation cost (Year 1 only) | B14: 500000 | C14: Capex / setup / migration cost, incurred once
A15: Recurring operating cost per year (Year 1 base) | B15: 160000 | C15: License, infra, support cost; escalates by cost escalation rate in Yr2/3
A16: Additional FTE / headcount cost per year | B16: 0 | C16: Optional - leave 0 if not applicable
A18: Benefit Inputs (steady-state / full run-rate, ANNUAL)
A19: Cost savings (annual, at full run-rate) | B19: 800000 | C19: e.g. reduced manual effort, lower error/fraud losses, infra savings
A20: Revenue uplift / productivity gain (annual, at full run-rate) | B20: 300000 | C20: e.g. faster processing, more throughput, new capability
A21: Risk reduction benefit (annual, at full run-rate) | B21: 150000 | C21: e.g. avoided losses, compliance penalty avoidance

Sheet 3-Year Model
A1: 3-Year Benefit Calculation Model
A3: ($ unless noted)
A4: Line Item | B4: Year 1 | C4: Year 2 | D4: Year 3 | E4: 3-Year Total
A6: COSTS
A7: One-time implementation cost | B7: =Assumptions!$B$14 -> 500000 | C7: 0 | D7: 0 | E7: =SUM(B7:D7) -> 500000
A8: Recurring operating cost (escalated) | B8: =Assumptions!$B$15*1 -> 160000 | C8: =Assumptions!$B$15*(1+Assumptions!$B$5) -> 164800 | D8: =Assumptions!$B$15*(1+Assumptions!$B$5)^2 -> 169744 | E8: =SUM(B8:D8) -> 494544
A9: Additional FTE / headcount cost (escalated) | B9: =Assumptions!$B$16*1 -> 0 | C9: =Assumptions!$B$16*(1+Assumptions!$B$5) -> 0 | D9: =Assumptions!$B$16*(1+Assumptions!$B$5)^2 -> 0 | E9: =SUM(B9:D9) -> 0
A10: Total Costs | B10: =SUM(B7:B9) -> 660000 | C10: =SUM(C7:C9) -> 164800 | D10: =SUM(D7:D9) -> 169744 | E10: =SUM(B10:D10) -> 994544
A12: BENEFITS
A13: Cost savings | B13: =Assumptions!$B$19*Assumptions!$B$8 -> 320000 | C13: =Assumptions!$B$19*Assumptions!$B$9 -> 600000 | D13: =Assumptions!$B$19*Assumptions!$B$10 -> 800000 | E13: =SUM(B13:D13) -> 1720000
A14: Revenue uplift / productivity gain | B14: =Assumptions!$B$20*Assumptions!$B$8 -> 120000 | C14: =Assumptions!$B$20*Assumptions!$B$9 -> 225000 | D14: =Assumptions!$B$20*Assumptions!$B$10 -> 300000 | E14: =SUM(B14:D14) -> 645000
A15: Risk reduction benefit | B15: =Assumptions!$B$21*Assumptions!$B$8 -> 60000 | C15: =Assumptions!$B$21*Assumptions!$B$9 -> 112500 | D15: =Assumptions!$B$21*Assumptions!$B$10 -> 150000 | E15: =SUM(B15:D15) -> 322500
A16: Total Benefits | B16: =SUM(B13:B15) -> 500000 | C16: =SUM(C13:C15) -> 937500 | D16: =SUM(D13:D15) -> 1250000 | E16: =SUM(B16:D16) -> 2687500
A18: Net Benefit (Benefits – Costs) | B18: =B16-B10 -> -160000 | C18: =C16-C10 -> 772700 | D18: =D16-D10 -> 1080256 | E18: =SUM(B18:D18) -> 1692956
A19: Cumulative Net Benefit | B19: =B18 -> -160000 | C19: =B19+C18 -> 612700 | D19: =C19+D18 -> 1692956 | E19: =D19 -> 1692956
A21: DISCOUNTING & NPV
A22: Discount factor (annual) | B22: =1/(1+Assumptions!$B$4)^1 -> 0.90909091 | C22: =1/(1+Assumptions!$B$4)^2 -> 0.82644628 | D22: =1/(1+Assumptions!$B$4)^3 -> 0.7513148
A23: Discounted Net Benefit | B23: =B18*B22 -> -145454.55 | C23: =C18*C22 -> 638595.04 | D23: =D18*D22 -> 811612.32 | E23: =SUM(B23:D23) -> 1304752.8
A24: Cumulative Discounted Net Benefit (running NPV) | B24: =B23 -> -145454.55 | C24: =B24+C23 -> 493140.5 | D24: =C24+D23 -> 1304752.8 | E24: =D24 -> 1304752.8

Sheet Summary
A1: Summary & Key Outputs
A3: Metric | B3: Value | C3: Notes
A4: Total Cost (3 years) | B4: ='3-Year Model'!E10 -> 994544 | C4: Sum of implementation + recurring + headcount costs
A5: Total Benefit (3 years) | B5: ='3-Year Model'!E16 -> 2687500 | C5: Sum of all benefit categories across 3 years
A6: Total Net Benefit (3 years, undiscounted) | B6: ='3-Year Model'!E18 -> 1692956 | C6: Total Benefit – Total Cost
A7: NPV of Net Benefit (discounted) | B7: ='3-Year Model'!E24 -> 1304752.8 | C7: Discounted at the annual rate set in Assumptions
A8: ROI % (3-year) | B8: =B6/B4 -> 1.7022434 | C8: Net Benefit ÷ Total Cost
A9: Benefit-Cost Ratio | B9: =B5/B4 -> 2.7022434 | C9: Total Benefit ÷ Total Cost
A11: Payback Period
A12: Payback period (years, undiscounted cumulative) | B12: =SUMPRODUCT(--('3-Year Model'!B19:D19<=0))+IF(SUMPRODUCT(--('3-Year Model'!B19:D19<=0))<3,-INDEX('3-Year Model'!B19:D19,SUMPRODUCT(--('3-Year Model'!B19:D19<=0)))/INDEX('3-Year Model'!B18:D18,SUMPRODUCT(--('3-Year Model'!B19:D19<=0))+1),0) -> 1.2070661 | C12: Full years where cumulative net benefit stayed negative, plus fraction of the next year needed to reach breakeven
A14: Year-by-Year Breakdown
A15: Year | B15: Net Benefit | C15: Cumulative Net Benefit
A16: Year 1 | B16: ='3-Year Model'!B18 -> -160000 | C16: ='3-Year Model'!B19 -> -160000
A17: Year 2 | B17: ='3-Year Model'!C18 -> 772700 | C17: ='3-Year Model'!C19 -> 612700
A18: Year 3 | B18: ='3-Year Model'!D18 -> 1080256 | C18: ='3-Year Model'!D19 -> 1692956
