Workbook

Sheet Assumptions
A1: 3-Year Benefit Calculation Model — Assumptions
A3: Financial Assumptions
A4: Annual discount rate (cost of capital) | B4: 0.1 | C4: Used to compute NPV of net benefits
A5: Annual cost escalation rate | B5: 0.03 | C5: Applied to recurring/operating costs each year
A7: Benefit Realization Ramp-Up (% of full run-rate benefit achieved)
A8: Year 1 realization % | B8: 0.4
A9: Year 2 realization % | B9: 0.75
A10: Year 3 realization % | B10: 1
A11: → Adjust these if benefit adoption ramps up over time (typical for process/tech rollouts)
A13: Cost Inputs
A14: One-time implementation cost (Year 1, Q1) | B14: 500000 | C14: Capex / setup / migration cost, incurred once
A15: Recurring operating cost per quarter (Year 1 base) | B15: 40000 | C15: License, infra, support cost per quarter; escalates by cost escalation rate in Yr2/3
A16: Additional FTE / headcount cost per quarter | B16: 0 | C16: Optional - leave 0 if not applicable
A18: Benefit Inputs (steady-state / full run-rate, ANNUAL)
A19: Cost savings (annual, at full run-rate) | B19: 800000 | C19: e.g. reduced manual effort, lower error/fraud losses, infra savings
A20: Revenue uplift / productivity gain (annual, at full run-rate) | B20: 300000 | C20: e.g. faster processing, more throughput, new capability
A21: Risk reduction benefit (annual, at full run-rate) | B21: 150000 | C21: e.g. avoided losses, compliance penalty avoidance

Sheet 3-Year Model
A1: 3-Year Benefit Calculation Model
A3: ($ unless noted) | B3: Year 1 | G3: Year 2 | L3: Year 3 | Q3: 3-Year Total
A4: Line Item | B4: Q1 | C4: Q2 | D4: Q3 | E4: Q4 | F4: Year Total | G4: Q1 | H4: Q2 | I4: Q3 | J4: Q4 | K4: Year Total | L4: Q1 | M4: Q2 | N4: Q3 | O4: Q4 | P4: Year Total
A6: COSTS
A7: One-time implementation cost | B7: =Assumptions!$B$14 -> 500000 | C7: 0 | D7: 0 | E7: 0 | F7: =SUM(B7:E7) -> 500000 | G7: 0 | H7: 0 | I7: 0 | J7: 0 | K7: =SUM(G7:J7) -> 0 | L7: 0 | M7: 0 | N7: 0 | O7: 0 | P7: =SUM(L7:O7) -> 0 | Q7: =F7+K7+P7 -> 500000
A8: Recurring operating cost (escalated) | B8: =Assumptions!$B$15*1 -> 40000 | C8: =Assumptions!$B$15*1 -> 40000 | D8: =Assumptions!$B$15*1 -> 40000 | E8: =Assumptions!$B$15*1 -> 40000 | F8: =SUM(B8:E8) -> 160000 | G8: =Assumptions!$B$15*(1+Assumptions!$B$5) -> 41200 | H8: =Assumptions!$B$15*(1+Assumptions!$B$5) -> 41200 | I8: =Assumptions!$B$15*(1+Assumptions!$B$5) -> 41200 | J8: =Assumptions!$B$15*(1+Assumptions!$B$5) -> 41200 | K8: =SUM(G8:J8) -> 164800 | L8: =Assumptions!$B$15*(1+Assumptions!$B$5)^2 -> 42436 | M8: =Assumptions!$B$15*(1+Assumptions!$B$5)^2 -> 42436 | N8: =Assumptions!$B$15*(1+Assumptions!$B$5)^2 -> 42436 | O8: =Assumptions!$B$15*(1+Assumptions!$B$5)^2 -> 42436 | P8: =SUM(L8:O8) -> 169744 | Q8: =F8+K8+P8 -> 494544
A9: Additional FTE / headcount cost (escalated) | B9: =Assumptions!$B$16*1 -> 0 | C9: =Assumptions!$B$16*1 -> 0 | D9: =Assumptions!$B$16*1 -> 0 | E9: =Assumptions!$B$16*1 -> 0 | F9: =SUM(B9:E9) -> 0 | G9: =Assumptions!$B$16*(1+Assumptions!$B$5) -> 0 | H9: =Assumptions!$B$16*(1+Assumptions!$B$5) -> 0 | I9: =Assumptions!$B$16*(1+Assumptions!$B$5) -> 0 | J9: =Assumptions!$B$16*(1+Assumptions!$B$5) -> 0 | K9: =SUM(G9:J9) -> 0 | L9: =Assumptions!$B$16*(1+Assumptions!$B$5)^2 -> 0 | M9: =Assumptions!$B$16*(1+Assumptions!$B$5)^2 -> 0 | N9: =Assumptions!$B$16*(1+Assumptions!$B$5)^2 -> 0 | O9: =Assumptions!$B$16*(1+Assumptions!$B$5)^2 -> 0 | P9: =SUM(L9:O9) -> 0 | Q9: =F9+K9+P9 -> 0
A10: Total Costs | B10: =SUM(B7:B9) -> 540000 | C10: =SUM(C7:C9) -> 40000 | D10: =SUM(D7:D9) -> 40000 | E10: =SUM(E7:E9) -> 40000 | F10: =SUM(F7:F9) -> 660000 | G10: =SUM(G7:G9) -> 41200 | H10: =SUM(H7:H9) -> 41200 | I10: =SUM(I7:I9) -> 41200 | ... P10: =SUM(P7:P9) -> 169744 | Q10: =F10+K10+P10 -> 994544
A12: BENEFITS
A13: Cost savings | B13: =Assumptions!$B$19/4*Assumptions!$B$8 -> 80000 | C13: =Assumptions!$B$19/4*Assumptions!$B$8 -> 80000 | D13: =Assumptions!$B$19/4*Assumptions!$B$8 -> 80000 | E13: =Assumptions!$B$19/4*Assumptions!$B$8 -> 80000 | F13: =SUM(B13:E13) -> 320000 | G13: =Assumptions!$B$19/4*Assumptions!$B$9 -> 150000 | H13: =Assumptions!$B$19/4*Assumptions!$B$9 -> 150000 | I13: =Assumptions!$B$19/4*Assumptions!$B$9 -> 150000 | J13: =Assumptions!$B$19/4*Assumptions!$B$9 -> 150000 | K13: =SUM(G13:J13) -> 600000 | L13: =Assumptions!$B$19/4*Assumptions!$B$10 -> 200000 | M13: =Assumptions!$B$19/4*Assumptions!$B$10 -> 200000 | N13: =Assumptions!$B$19/4*Assumptions!$B$10 -> 200000 | O13: =Assumptions!$B$19/4*Assumptions!$B$10 -> 200000 | P13: =SUM(L13:O13) -> 800000 | Q13: =F13+K13+P13 -> 1720000
A14: Revenue uplift / productivity gain | B14: =Assumptions!$B$20/4*Assumptions!$B$8 -> 30000 | C14: =Assumptions!$B$20/4*Assumptions!$B$8 -> 30000 | D14: =Assumptions!$B$20/4*Assumptions!$B$8 -> 30000 | E14: =Assumptions!$B$20/4*Assumptions!$B$8 -> 30000 | F14: =SUM(B14:E14) -> 120000 | G14: =Assumptions!$B$20/4*Assumptions!$B$9 -> 56250 | H14: =Assumptions!$B$20/4*Assumptions!$B$9 -> 56250 | I14: =Assumptions!$B$20/4*Assumptions!$B$9 -> 56250 | J14: =Assumptions!$B$20/4*Assumptions!$B$9 -> 56250 | K14: =SUM(G14:J14) -> 225000 | L14: =Assumptions!$B$20/4*Assumptions!$B$10 -> 75000 | M14: =Assumptions!$B$20/4*Assumptions!$B$10 -> 75000 | N14: =Assumptions!$B$20/4*Assumptions!$B$10 -> 75000 | O14: =Assumptions!$B$20/4*Assumptions!$B$10 -> 75000 | P14: =SUM(L14:O14) -> 300000 | Q14: =F14+K14+P14 -> 645000
A15: Risk reduction benefit | B15: =Assumptions!$B$21/4*Assumptions!$B$8 -> 15000 | C15: =Assumptions!$B$21/4*Assumptions!$B$8 -> 15000 | D15: =Assumptions!$B$21/4*Assumptions!$B$8 -> 15000 | E15: =Assumptions!$B$21/4*Assumptions!$B$8 -> 15000 | F15: =SUM(B15:E15) -> 60000 | G15: =Assumptions!$B$21/4*Assumptions!$B$9 -> 28125 | H15: =Assumptions!$B$21/4*Assumptions!$B$9 -> 28125 | I15: =Assumptions!$B$21/4*Assumptions!$B$9 -> 28125 | J15: =Assumptions!$B$21/4*Assumptions!$B$9 -> 28125 | K15: =SUM(G15:J15) -> 112500 | L15: =Assumptions!$B$21/4*Assumptions!$B$10 -> 37500 | M15: =Assumptions!$B$21/4*Assumptions!$B$10 -> 37500 | N15: =Assumptions!$B$21/4*Assumptions!$B$10 -> 37500 | O15: =Assumptions!$B$21/4*Assumptions!$B$10 -> 37500 | P15: =SUM(L15:O15) -> 150000 | Q15: =F15+K15+P15 -> 322500
A16: Total Benefits | B16: =SUM(B13:B15) -> 125000 | C16: =SUM(C13:C15) -> 125000 | D16: =SUM(D13:D15) -> 125000 | E16: =SUM(E13:E15) -> 125000 | F16: =SUM(F13:F15) -> 500000 | G16: =SUM(G13:G15) -> 234375 | H16: =SUM(H13:H15) -> 234375 | I16: =SUM(I13:I15) -> 234375 | ... P16: =SUM(P13:P15) -> 1250000 | Q16: =F16+K16+P16 -> 2687500
A18: Net Benefit (Benefits – Costs) | B18: =B16-B10 -> -415000 | C18: =C16-C10 -> 85000 | D18: =D16-D10 -> 85000 | E18: =E16-E10 -> 85000 | F18: =F16-F10 -> -160000 | G18: =G16-G10 -> 193175 | H18: =H16-H10 -> 193175 | I18: =I16-I10 -> 193175 | ... P18: =P16-P10 -> 1080256 | Q18: =F18+K18+P18 -> 1692956
A19: Cumulative Net Benefit | B19: =B18 -> -415000 | C19: =B19+C18 -> -330000 | D19: =C19+D18 -> -245000 | E19: =D19+E18 -> -160000 | F19: =E19 -> -160000 | G19: =E19+G18 -> 33175 | H19: =G19+H18 -> 226350 | I19: =H19+I18 -> 419525 | J19: =I19+J18 -> 612700 | K19: =J19 -> 612700 | L19: =J19+L18 -> 882764 | M19: =L19+M18 -> 1152828 | N19: =M19+N18 -> 1422892 | O19: =N19+O18 -> 1692956 | P19: =O19 -> 1692956 | Q19: =P19 -> 1692956
A21: DISCOUNTING & NPV
A22: Discount factor (quarterly) | B22: =1/(1+((1+Assumptions!$B$4)^(1/4)-1))^1 -> 0.97645409 | C22: =1/(1+((1+Assumptions!$B$4)^(1/4)-1))^2 -> 0.95346259 | D22: =1/(1+((1+Assumptions!$B$4)^(1/4)-1))^3 -> 0.93101244 | E22: =1/(1+((1+Assumptions!$B$4)^(1/4)-1))^4 -> 0.90909091 | G22: =1/(1+((1+Assumptions!$B$4)^(1/4)-1))^5 -> 0.88768554 | H22: =1/(1+((1+Assumptions!$B$4)^(1/4)-1))^6 -> 0.86678417 | I22: =1/(1+((1+Assumptions!$B$4)^(1/4)-1))^7 -> 0.84637495 | J22: =1/(1+((1+Assumptions!$B$4)^(1/4)-1))^8 -> 0.82644628 | L22: =1/(1+((1+Assumptions!$B$4)^(1/4)-1))^9 -> 0.80698685 | M22: =1/(1+((1+Assumptions!$B$4)^(1/4)-1))^10 -> 0.78798561 | N22: =1/(1+((1+Assumptions!$B$4)^(1/4)-1))^11 -> 0.76943177 | O22: =1/(1+((1+Assumptions!$B$4)^(1/4)-1))^12 -> 0.7513148
A23: Discounted Net Benefit | B23: =B18*B22 -> -405228.45 | C23: =C18*C22 -> 81044.32 | D23: =D18*D22 -> 79136.058 | E23: =E18*E22 -> 77272.727 | F23: =SUM(B23:E23) -> -167775.34 | G23: =G18*G22 -> 171478.65 | H23: =H18*H22 -> 167441.03 | I23: =I18*I22 -> 163498.48 | J23: =J18*J22 -> 159648.76 | K23: =SUM(G23:J23) -> 662066.93 | L23: =L18*L22 -> 217938.1 | M23: =M18*M22 -> 212806.55 | N23: =N18*N22 -> 207795.82 | O23: =O18*O22 -> 202903.08 | P23: =SUM(L23:O23) -> 841443.55 | Q23: =F23+K23+P23 -> 1335735.1
A24: Cumulative Discounted Net Benefit (running NPV) | B24: =B23 -> -405228.45 | C24: =B24+C23 -> -324184.13 | D24: =C24+D23 -> -245048.07 | E24: =D24+E23 -> -167775.34 | F24: =E24 -> -167775.34 | G24: =E24+G23 -> 3703.3114 | H24: =G24+H23 -> 171144.34 | I24: =H24+I23 -> 334642.82 | J24: =I24+J23 -> 494291.59 | K24: =J24 -> 494291.59 | L24: =J24+L23 -> 712229.68 | M24: =L24+M23 -> 925036.23 | N24: =M24+N23 -> 1132832.1 | O24: =N24+O23 -> 1335735.1 | P24: =O24 -> 1335735.1 | Q24: =P24 -> 1335735.1

Sheet Summary
A1: Summary & Key Outputs
A3: Metric | B3: Value | C3: Notes
A4: Total Cost (3 years) | B4: ='3-Year Model'!Q10 -> 994544 | C4: Sum of implementation + recurring + headcount costs
A5: Total Benefit (3 years) | B5: ='3-Year Model'!Q16 -> 2687500 | C5: Sum of all benefit categories across 3 years
A6: Total Net Benefit (3 years, undiscounted) | B6: ='3-Year Model'!Q18 -> 1692956 | C6: Total Benefit – Total Cost
A7: NPV of Net Benefit (discounted) | B7: ='3-Year Model'!Q24 -> 1335735.1 | C7: Discounted at the annual rate set in Assumptions
A8: ROI % (3-year) | B8: =B6/B4 -> 1.7022434 | C8: Net Benefit ÷ Total Cost
A9: Benefit-Cost Ratio | B9: =B5/B4 -> 2.7022434 | C9: Total Benefit ÷ Total Cost
A11: Payback Period
A12: Payback period (in quarters, undiscounted cumulative) | B12: =SUMPRODUCT(--('3-Year Model'!B19:E19<=0))+SUMPRODUCT(--('3-Year Model'!G19:J19<=0))+SUMPRODUCT(--('3-Year Model'!L19:O19<=0))+1 -> 5 | C12: First quarter where cumulative net benefit turns positive
A13: Payback period (Year / Quarter) | B13: ="Year "&ROUNDUP(B12/4,0)&", Q"&(B12-(ROUNDUP(B12/4,0)-1)*4) -> Year 2, Q1
A15: Year-by-Year Breakdown
A16: Year | B16: Net Benefit | C16: Cumulative Net Benefit
A17: Year 1 | B17: ='3-Year Model'!F18 -> -160000 | C17: ='3-Year Model'!F19 -> -160000
A18: Year 2 | B18: ='3-Year Model'!K18 -> 772700 | C18: ='3-Year Model'!K19 -> 612700
A19: Year 3 | B19: ='3-Year Model'!P18 -> 1080256 | C19: ='3-Year Model'!P19 -> 1692956
