Workbook

Sheet Read Me
A1: US ATM — Out-of-Cash (OOC) Avoidance Benefit Model
A3: Purpose | B3: Quantifies the annual $ benefit to a US bank of preventing ATM out-of-cash (OOC) events — e.g. via recycling ATM conversion, better replenishment scheduling, or forecasting improvements. Benefit is split into a HARD total (auditable, dollar-backed) and a SOFT sensitivity band (dissatisfaction/reputational, shown separately so it is never silently blended into the headline number).
A5: Benefit categories included
A6: Fee & interchange revenue | B6: Surcharge + network interchange lost on the non-customer share of transactions at your ATM. Your own customers generate $0 here — no surcharge is charged to account holders and no interchange applies on an on-us transaction.
A7: Channel cost-shifting | B7: Transactions that migrate to a more expensive channel (teller/branch) when the ATM is down; benefit = txns migrated x (teller cost − ATM cost).
A8: CIT dispatch premium | B8: The premium of an unscheduled/emergency cash-in-transit dispatch over what a normal scheduled route stop would have cost anyway.
A9: Complaint/dispute handling | B9: Cost of tickets, Reg E disputes, or CFPB complaints generated by a share of OOC events.
A10: Soft cost (sensitivity band only) | B10: Illustrative low/mid/high dissatisfaction-reputational cost, shown separately — not included in the hard total or the headline payback math.
A12: Sheets in this workbook
A13: Assumptions | B13: All editable inputs. Yellow cells = your inputs.
A14: OOC_Benefit | B14: Builds cost-per-event for each hard-cost category, then scales to fleet-wide annual $.
A15: Summary | B15: Hard-cost total, soft-cost band shown alongside it, and the investment case (payback, ROI) built on the conservative hard-only number.
A17: Color legend
A18: Yellow fill, blue text | B18: Input — edit these.
A19: Black text | B19: Formula, calculated within the same sheet.
A20: Green text | B20: Formula linking to another sheet.
A22: Example values | B22: Pre-filled illustrative starting values (e.g. $3.22 average industry surcharge, $0.45 average network interchange tier). Replace with your own bank's posted surcharge, your actual interchange tier, and your own observed OOC rates and transaction mix before relying on the output — the industry averages are a starting point only, not your numbers.

Sheet Assumptions
A1: Key Assumptions & Inputs
A2: Edit only the yellow cells. Figures are per-ATM-per-month unless stated otherwise.
A4: A. Fleet Parameters
B5: Value | C5: Unit
A6: Number of ATMs in scope (recycling conversion / scheduling improvement) | B6: 100 | C6: ATMs
A7: Analysis period | B7: 12 | C7: months
A8: Investment cost per ATM (one-time) | B8: 350000 | C8: $ per ATM
A10: B. OOC Event Rates
B11: Baseline | C11: Improved (post-fix) | D11: Unit
A12: OOC events per ATM per month | B12: 1.2 | C12: 0.3 | D12: events/ATM/month
A13: Avg. transactions lost per OOC event (until replenished) | B13: 45 | D13: txns/event
A15: C. Fee & Interchange Revenue (US) — applies ONLY to non-customer transaction share
B16: Value | C16: Unit
A17: % of ATM transactions from non-account-holders (surcharge-eligible) | B17: 0.25 | D17: own customers = 0% here — no surcharge/interchange on an on-us transaction
A18: Surcharge charged to non-customers per transaction | B18: 3.22 | D18: $/txn — replace with your bank's actual posted surcharge (industry avg. shown)
A19: Network interchange (cash disbursement reimbursement) earned per non-customer txn | B19: 0.45 | D19: $/txn — replace with your actual network tier (industry range ~$0.30-$0.60)
A21: D. Channel Cost-Shifting
B22: Value | C22: Unit
A23: % of lost ATM transactions that migrate to teller/branch (rest are abandoned/lost) | B23: 0.4
A24: Cost per teller/branch transaction | B24: 4.25 | D24: $/txn — use your own unit-cost-by-channel figure
A25: Cost per ATM self-service transaction (baseline channel cost) | B25: 0.35 | D25: $/txn
A27: E. CIT Dispatch Premium
B28: Value | C28: Unit
A29: Cost of a scheduled CIT stop (would occur anyway on the normal route) | B29: 300 | D29: $/stop
A30: Cost of an unscheduled/emergency CIT dispatch | B30: 2500 | D30: $/dispatch
A32: F. Complaint / Dispute Handling
B33: Value | C33: Unit
A34: % of OOC events that generate a formal complaint/dispute ticket | B34: 0.05
A35: Avg. cost to handle a complaint/dispute ticket | B35: 45 | D35: $/ticket — agent time + any goodwill credit issued
A37: G. Soft Cost — Dissatisfaction / Reputational (sensitivity band, NOT in hard total)
B38: Low | C38: Mid | D38: High
A39: Illustrative dissatisfaction/reputational cost per OOC event | B39: 0 | C39: 75 | D39: 150

Sheet OOC_Benefit
A1: Benefit from Avoided Out-of-Cash (OOC) Events — US ATM Fleet
A2: All inputs are linked (green) from the Assumptions sheet. Nothing here needs editing.
A4: 1. Hard Cost per OOC Event — Build-Up
A5: Fee & interchange revenue lost (txns lost x non-customer % x (surcharge + interchange)) | B5: =Assumptions!$B$13*Assumptions!$B$17*(Assumptions!$B$18+Assumptions!$B$19) -> 41.2875
A6: Channel cost-shifting avoided (txns lost x migrate % x (teller cost − ATM cost)) | B6: =Assumptions!$B$13*Assumptions!$B$23*(Assumptions!$B$24-Assumptions!$B$25) -> 70.2
A7: CIT dispatch premium avoided (emergency dispatch cost − scheduled stop cost) | B7: =Assumptions!$B$30-Assumptions!$B$29 -> 2200
A8: Complaint/dispute handling cost avoided (complaint % x cost per ticket) | B8: =Assumptions!$B$34*Assumptions!$B$35 -> 2.25
A9: Total HARD cost per OOC event | B9: =B5+B6+B7+B8 -> 2313.7375
A11: 2. Hard-Cost Monthly & Annual Benefit (per ATM, then fleet-wide)
B12: Baseline | C12: Improved (post-fix) | D12: Reduction / Benefit
A13: OOC events per ATM per month | B13: =Assumptions!$B$12 -> 1.2 | C13: =Assumptions!$C$12 -> 0.3 | D13: =B13-C13 -> 0.9
A14: Hard cost per event ($) | B14: =$B$9 -> 2313.7375 | C14: =$B$9 -> 2313.7375
A15: Monthly hard cost per ATM | B15: =B13*B14 -> 2776.485 | C15: =C13*C14 -> 694.12125 | D15: =B15-C15 -> 2082.3637
A16: Annual hard cost per ATM (x analysis period) | B16: =B15*Assumptions!$B$7 -> 33317.82 | C16: =C15*Assumptions!$B$7 -> 8329.455 | D16: =B16-C16 -> 24988.365
A17: Fleet-wide annual hard cost (x number of ATMs) | B17: =B16*Assumptions!$B$6 -> 3331782 | C17: =C16*Assumptions!$B$6 -> 832945.5 | D17: =B17-C17 -> 2498836.5
A19: 3. HARD Result (auditable — used for the investment case)
A20: Annual $ Benefit — Avoided OOC Events, HARD COSTS ONLY (fleet-wide) | B20: =D17 -> 2498836.5
A22: 4. SOFT Cost Sensitivity Band (dissatisfaction/reputational — NOT in hard total above)
B23: Low | C23: Mid | D23: High
A24: Soft cost per OOC event | B24: =Assumptions!$B$39 -> 0 | C24: =Assumptions!$C$39 -> 75 | D24: =Assumptions!$D$39 -> 150
A25: Fleet-wide annual soft-cost benefit (reduction in events x soft cost x fleet x period) | B25: =D13*B24*Assumptions!$B$7*Assumptions!$B$6 -> 0 | C25: =D13*C24*Assumptions!$B$7*Assumptions!$B$6 -> 81000 | D25: =D13*D24*Assumptions!$B$7*Assumptions!$B$6 -> 162000
A27: The soft-cost band is illustrative and intentionally excluded from the hard total and the investment-case math on the Summary tab. Report it as a range alongside the hard number, not folded into it, unless your finance team has an actual churn/CLV-based cost to substitute.

Sheet Summary
A1: US ATM OOC Avoidance — Benefit Summary
A2: Pulls results from OOC_Benefit. Edit the Assumptions sheet only.
A4: 1. Annual Benefit — Hard vs. Soft
B5: Low | C5: Mid | D5: High
A6: HARD cost avoidance (fee/interchange + channel shift + CIT premium + complaints) | B6: =OOC_Benefit!$B$20 -> 2498836.5 | C6: =OOC_Benefit!$B$20 -> 2498836.5 | D6: =OOC_Benefit!$B$20 -> 2498836.5
A7: SOFT cost avoidance (dissatisfaction/reputational — illustrative band) | B7: =OOC_Benefit!$B$25 -> 0 | C7: =OOC_Benefit!$C$25 -> 81000 | D7: =OOC_Benefit!$D$25 -> 162000
A8: Total (hard + soft) — for illustration only | B8: =B6+B7 -> 2498836.5 | C8: =C6+C7 -> 2579836.5 | D8: =D6+D7 -> 2660836.5
A10: 2. Investment Case (built on HARD benefit only — conservative)
A11: Number of ATMs in scope | B11: =Assumptions!$B$6 -> 100
A12: Investment cost per ATM | B12: =Assumptions!$B$8 -> 350000
A13: Total fleet investment cost | B13: =Assumptions!$B$6*Assumptions!$B$8 -> 35000000
A14: Simple payback period (using HARD benefit) | B14: =B13/(B6/12) -> 168.07822 | C14: months
A15: 3-year net benefit (HARD benefit x3, less one-time investment cost) | B15: =(B6*3)-B13 -> -27503490
A16: 3-year ROI (%, HARD benefit only) | B16: =B15/B13 -> -0.78581401
A18: 3. Headline Result
A19: Total Annual $ Benefit of Preventing OOC Events (HARD, conservative) | B19: =B6 -> 2498836.5
A20: + Soft-cost sensitivity range (illustrative, shown separately) | B20: =OOC_Benefit!$B$25 -> 0 | C20: =OOC_Benefit!$C$25 -> 81000 | D20: =OOC_Benefit!$D$25 -> 162000
A22: Benefit = (baseline OOC rate − improved OOC rate) x cost per event x fleet size x period. The hard-cost total (fee/interchange, channel cost-shift, CIT premium, complaint handling) is auditable against real bank data. The soft-cost band is a labeled sensitivity range, not a point estimate, and is deliberately excluded from the payback/ROI math above so the investment case doesn't rest on an unverifiable number. Validate the improved-state OOC rate against pilot data before using this for a funding decision.
